stoy/VERSION
stoy/__init__.py
stoy/stoy.py
stoy-0.0.16.data/scripts/generate-token
stoy-0.0.16.data/scripts/stoy
stoy-0.0.16.dist-info/LICENSE
stoy-0.0.16.dist-info/METADATA
stoy-0.0.16.dist-info/WHEEL
stoy-0.0.16.dist-info/top_level.txt
stoy-0.0.16.dist-info/RECORD
