Metadata-Version: 2.1
Name: stoy
Version: 0.0.16
Summary: Jupyter Server auto stop
Home-page: https://github.com/RomanKosobrodov/stoy
Author: Roman Kosobrodov
Author-email: roman@kosobrodov.net
License: MIT
Platform: UNKNOWN
Classifier: Programming Language :: Python :: 3
Classifier: Operating System :: OS Independent
Requires-Python: >=3.6
License-File: LICENSE
Requires-Dist: aiohttp (>=3.8)
Requires-Dist: boto3 (>=1.20)
